lQ_/__init__.py
lQ_/main.py
lQQQQQQQQQQQQQQQ-0.0.1.dist-info/METADATA
lQQQQQQQQQQQQQQQ-0.0.1.dist-info/WHEEL
lQQQQQQQQQQQQQQQ-0.0.1.dist-info/top_level.txt
lQQQQQQQQQQQQQQQ-0.0.1.dist-info/RECORD
