Metadata-Version: 2.1
Name: lQQQQQQQQQQQQQQQ
Version: 0.0.1
Summary: linear eq
Author: Ali Rachidi
Author-email: arachid1@jhu.edu
License: MIT
Classifier: Programming Language :: Python :: 3.7
Classifier: Programming Language :: Python :: 3.9
Classifier: License :: OSI Approved :: MIT License
Requires-Python: >=3.7,<3.10
Provides-Extra: all
